{"RespCode":"000","RespDescription":"Your transaction is processing to other bank.","ErrorMsg":null,"FromAccount":"0005010100002441","FromAcctName":"U AR YU","ToAccount":"45369064235763168","ToAcctName":"ttt","TranAmount":"10,000.00","ChargeCode":null,"ChargeAmount":"800.00","TotalAmount":"10,800.00","Discount":null,"TranDate":"2020-07-10T00:00:00.000","ValueDate":"13/07/2020 10:23:51","TranID":"AB1661","NRC":"","Phone":null,"TranCountAmtID":"","Remark":"other bank","OurChargeAmt":0.0,"Oth_Bank_ChargeAmt":0.0}
